sekaiworld/scores/__init__.py
sekaiworld/scores/__main__.py
sekaiworld/scores/drawing.py
sekaiworld/scores/line.py
sekaiworld/scores/lyric.py
sekaiworld/scores/meta.py
sekaiworld/scores/rebase.py
sekaiworld/scores/score.py
sekaiworld/scores/css/default.css
sekaiworld/scores/notes/__init__.py
sekaiworld/scores/notes/base.py
sekaiworld/scores/notes/directional.py
sekaiworld/scores/notes/event.py
sekaiworld/scores/notes/note.py
sekaiworld/scores/notes/slide.py
sekaiworld/scores/notes/tap.py
sekaiworld/scores/types/__init__.py
sekaiworld/scores/types/fraction.py
sekaiworld.scores-0.1.10.dist-info/LICENSE
sekaiworld.scores-0.1.10.dist-info/METADATA
sekaiworld.scores-0.1.10.dist-info/WHEEL
sekaiworld.scores-0.1.10.dist-info/top_level.txt
sekaiworld.scores-0.1.10.dist-info/RECORD
