Metadata-Version: 2.1
Name: sekaiworld.scores
Version: 0.1.10
Summary: Render Project Sekai score files (sus) to images (svg). Powered by pjsekai/scores.
Author-email: Sekai World <dev@sekai.best>
License: MIT License
Project-URL: Homepage, https://github.com/Sekai-World/pjsekai-scores
Project-URL: Documentation, https://github.com/Sekai-World/pjsekai-scores/wiki
Project-URL: Bug Tracker, https://github.com/Sekai-World/pjsekai-scores/issues
Keywords: Project Sekai,pjsekai,SUS
Classifier: Programming Language :: Python :: 3
Classifier: License :: OSI Approved :: MIT License
Classifier: Operating System :: OS Independent
Requires-Python: >=3.10
License-File: LICENSE
Requires-Dist: svgwrite
